dtocean_app/__init__.py
dtocean_app-2.1.1.dist-info/METADATA
dtocean_app-2.1.1.dist-info/WHEEL
dtocean_app-2.1.1.dist-info/RECORD
