Metadata-Version: 2.1
Name: dtocean-app
Version: 2.1.1
Summary: Main graphical application for the DTOcean tools
Author: Mathew Topper
Author-email: damm_horse@yahoo.co.uk
Requires-Python: >=3.13,<4.0
Classifier: Programming Language :: Python :: 3
Classifier: Programming Language :: Python :: 3.13
